Metadata-Version: 1.0
Name: drcompare
Version: 2.1.0
Summary: a Python module to compare the images given in the input CSV file
Home-page: UNKNOWN
Author: Ravjot Singh
Author-email: ravjotsingh9@yahoo.com
License: UNKNOWN
Platform: UNKNOWN
